<?xml version="1.0" encoding="UTF-8"?>
<objects serializationModel="Studio.02.00.00">
	<object class="AudioFile" id="{3aaedb20-0a52-46a3-9547-7f86d310e4d7}">
		<property name="assetPath">
			<value>isa_hitenemy.mp3</value>
		</property>
		<property name="frequencyInKHz">
			<value>44.0999985</value>
		</property>
		<property name="channelCount">
			<value>2</value>
		</property>
		<property name="length">
			<value>1.0710204081632653</value>
		</property>
		<relationship name="masterAssetFolder">
			<destination>{032329ca-4ff9-464c-8786-500b04b7537e}</destination>
		</relationship>
	</object>
</objects>
